ask_claude/__init__.py
ask_claude/hello.py
ask_claude-0.0.1.dist-info/licenses/LICENSE
ask_claude-0.0.1.dist-info/METADATA
ask_claude-0.0.1.dist-info/WHEEL
ask_claude-0.0.1.dist-info/top_level.txt
ask_claude-0.0.1.dist-info/RECORD
