Metadata-Version: 2.4
Name: ask_claude
Version: 0.0.1
Summary: Coming soon!
Author: Katherine Rosenfeld
Requires-Python: >=3.10
License-File: LICENSE
Dynamic: license-file
